buildcdf/__init__.py
buildcdf/buildcdf.py
buildcdf-1.dist-info/LICENSE
buildcdf-1.dist-info/METADATA
buildcdf-1.dist-info/WHEEL
buildcdf-1.dist-info/top_level.txt
buildcdf-1.dist-info/RECORD
