Metadata-Version: 2.1
Name: buildcdf
Version: 1
Summary: Python package to generate input data for Cumulative Distribution Function
Home-page: https://github.com/barsand/buildcdf
Author: Lucas Barsand
Author-email: barsandlucas@gmail.com
License: UNKNOWN
Platform: UNKNOWN
Classifier: Programming Language :: Python :: 3
Classifier: License :: OSI Approved :: MIT License
Classifier: Operating System :: OS Independent
Requires-Python: >=3.6
